homeman/__init__.py
homeman/homeman.py
homeman-1.0.3.dist-info/LICENSE
homeman-1.0.3.dist-info/METADATA
homeman-1.0.3.dist-info/WHEEL
homeman-1.0.3.dist-info/entry_points.txt
homeman-1.0.3.dist-info/top_level.txt
homeman-1.0.3.dist-info/RECORD
