Metadata-Version: 2.1
Name: homeman
Version: 1.0.3
Summary: keep files synchronized between user home and your special home directory
Home-page: https://gitee.com/sunn4open/homeman.git
Author: sunn4room
Author-email: sunn4room@163.com
Classifier: Programming Language :: Python :: 3
Classifier: License :: OSI Approved :: MIT License
Classifier: Operating System :: OS Independent
License-File: LICENSE
Requires-Dist: colorama
